lib/__init__.py
lib/args.py
lib/base.py
lib/cache.py
lib/db_mysql.py
lib/db_sqlite.py
lib/disk.py
lib/distro.py
lib/dmidecode.py
lib/endoflifedate.py
lib/feedparser.py
lib/globals.py
lib/grassfish.py
lib/huawei.py
lib/human.py
lib/icinga.py
lib/infomaniak.py
lib/jitsi.py
lib/librenms.py
lib/net.py
lib/nodebb.py
lib/powershell.py
lib/psutil.py
lib/qts.py
lib/redfish.py
lib/rocket.py
lib/shell.py
lib/smb.py
lib/test.py
lib/time.py
lib/txt.py
lib/url.py
lib/veeam.py
lib/version.py
lib/wildfly.py
lib/winrm.py
linuxfabrik_lib-2024060401.dist-info/LICENSE
linuxfabrik_lib-2024060401.dist-info/METADATA
linuxfabrik_lib-2024060401.dist-info/WHEEL
linuxfabrik_lib-2024060401.dist-info/top_level.txt
linuxfabrik_lib-2024060401.dist-info/RECORD
