Metadata-Version: 2.1
Name: linuxfabrik-lib
Version: 2024060401
Summary: Python libraries used in various Linuxfabrik projects, including the 'Linuxfabrik Monitoring Plugins' project.
Author-email: "Linuxfabrik GmbH, Zurich, Switzerland" <info@linuxfabrik.ch>
License: This is free and unencumbered software released into the public domain.
Project-URL: Homepage, https://github.com/Linuxfabrik/lib
Project-URL: Documentation, https://github.com/Linuxfabrik/lib/blob/master/README.md
Project-URL: Source, https://github.com/Linuxfabrik/lib
Project-URL: Tracker, https://github.com/Linuxfabrik/lib/issues
Project-URL: Download, https://github.com/Linuxfabrik/lib/releases
Keywords: lib,libs,monitoring,monitoring plugins,icinga,nagios
Classifier: Development Status :: 6 - Mature
Classifier: Intended Audience :: Developers
Classifier: Intended Audience :: Education
Classifier: Intended Audience :: Healthcare Industry
Classifier: Intended Audience :: Information Technology
Classifier: Intended Audience :: Manufacturing
Classifier: Intended Audience :: Other Audience
Classifier: Intended Audience :: Science/Research
Classifier: Intended Audience :: System Administrators
Classifier: Intended Audience :: Telecommunications Industry
Classifier: License :: OSI Approved :: The Unlicense (Unlicense)
Classifier: Natural Language :: English
Classifier: Operating System :: OS Independent
Classifier: Programming Language :: Python
Classifier: Programming Language :: Python :: 3
Classifier: Topic :: Software Development :: Libraries
Classifier: Topic :: Software Development :: Libraries :: Python Modules
Classifier: Topic :: System
Classifier: Topic :: System :: Monitoring
Classifier: Topic :: System :: Networking :: Monitoring
Requires-Python: >=3.6
License-File: LICENSE
Requires-Dist: beautifulsoup4
Requires-Dist: lxml
Requires-Dist: netifaces
Requires-Dist: psutil
Requires-Dist: pymysql
Requires-Dist: pysmbclient
Requires-Dist: python-keystoneclient
Requires-Dist: python-novaclient
Requires-Dist: python-swiftclient
Requires-Dist: pywinrm
Requires-Dist: requests
Requires-Dist: smbprotocol
Requires-Dist: vici
Requires-Dist: xmltodict
